{"stats":{"minecraft:used":{"irons_spellbooks:inscription_table":1,"minecraft:spruce_slab":227,"iceandfire:dragon_skull_ice":7,"minecraft:chest":59,"minecraft:rotten_flesh":30,"minecraft:snowball":95,"minecraft:azure_bluet":1,"minecraft:spruce_boat":17,"minecraft:lava_bucket":3,"iceandfire:crackled_gravel":1,"iceandfire:copper_pickaxe":18,"minecraft:stone_brick_stairs":49,"minecraft:rabbit_stew":2,"iceandfire:armor_amythest_boots":2,"minecraft:bow":119,"minecraft:sweet_berries":102,"minecraft:furnace":17,"minecraft:cooked_cod":3,"minecraft:egg":1,"block_factorys_bosses:vase":1,"minecraft:mossy_stone_bricks":1,"minecraft:cactus":1,"minecraft:prismarine":2,"minecraft:blackstone":89,"iceandfire:dragonbone_sword_ice":476,"minecraft:wooden_pickaxe":14,"artifacts:eternal_steak":150,"iceandfire:dread_stone_bricks":2,"brewery:corn_seeds":7,"block_factorys_bosses:underwold_candles":2,"minecraft:oak_leaves":41,"minecraft:jungle_boat":1,"minecraft:golden_apple":7,"brewery:barrel_main":1,"minecraft:sand":3,"iceandfire:lightning_dragon_flesh":7,"irons_spellbooks:firefly_jar":1,"iceandfire:dread_sword":4,"minecraft:fire_charge":2,"minecraft:nether_wart_block":1,"minecraft:smithing_table":5,"minecraft:poisonous_potato":2,"minecraft:stone_sword":151,"brewery:wooden_brewingstation":1,"block_factorys_bosses:wall_torch":1,"minecraft:cooked_salmon":1,"minecraft:netherrack":188,"minecraft:orange_bed":3,"minecraft:torch":150,"minecraft:brewing_stand":2,"minecraft:anvil":2,"minecraft:nether_brick_slab":3,"minecraft:nether_brick_stairs":5,"travelersbackpack:gold":43,"minecraft:iron_axe":591,"brewery:beer_barley":2,"minecraft:jungle_log":1,"travelersbackpack:squid":22,"minecraft:bamboo":1,"create:encased_chain_drive":3,"minecraft:basalt":20,"minecraft:goat_horn":1,"minecraft:cobbled_deepslate":17,"minecraft:acacia_planks":43,"minecraft:wheat_seeds":34,"alexsmobs:cooked_catfish":133,"minecraft:water_bucket":485,"block_factorys_bosses:underworld_tall_candles":10,"iceandfire:crackled_stone":1,"brewery:silo_wood":2,"minecraft:fletching_table":5,"iceandfire:dragon_skull_lightning":13,"brewery:beer_wheat":11,"minecraft:cracked_stone_bricks":19,"minecraft:polished_blackstone_bricks":94,"minecraft:crafting_table":32,"minecraft:oak_slab":3,"minecraft:white_bed":15,"minecraft:cod":1,"minecraft:spruce_log":4,"minecraft:oak_log":1,"iceandfire:armor_amythest_helmet":3,"minecraft:diamond_pickaxe":217,"alexsmobs:kangaroo_meat":6,"minecraft:iron_pickaxe":1500,"travelersbackpack:white_sleeping_bag":1,"iceandfire:cyclops_skull":3,"minecraft:spruce_sapling":14,"travelersbackpack:standard":10,"minecraft:cobblestone":182,"minecraft:potion":1,"minecraft:crimson_stairs":26,"minecraft:porkchop":10,"minecraft:cooked_porkchop":34,"minecraft:candle":34,"iceandfire:tide_trident":14,"minecraft:oak_sign":4,"minecraft:shield":160,"minecraft:iron_sword":2,"minecraft:mutton":8,"minecraft:carrot":1,"minecraft:beehive":3,"travelersbackpack:iron":7,"minecraft:tuff":3,"minecraft:iron_helmet":1,"iceandfire:armor_amythest_chestplate":1,"minecraft:stone_bricks":8,"minecraft:golden_sword":1,"minecraft:red_carpet":9,"minecraft:skeleton_skull":1,"minecraft:gray_bed":1,"iceandfire:pixie_jar_empty":2,"alexsmobs:raw_catfish":3,"minecraft:chiseled_polished_blackstone":1,"brewery:cabinet":4,"minecraft:stone_pickaxe":252,"minecraft:chainmail_helmet":1,"minecraft:white_wool":12,"travelersbackpack:quartz":1,"minecraft:crossbow":79,"iceandfire:dragonbone_sword_lightning":801,"minecraft:stone_brick_wall":1,"simplyswords:iron_greathammer":599,"waystones:waystone":2,"minecraft:melon_slice":164,"minecraft:bread":312,"minecraft:cyan_bed":12,"brewery:hops_seeds":9,"minecraft:gravel":32,"iceandfire:ice_dragon_flesh":9,"alexsmobs:cooked_moose_ribs":3,"immersive_aircraft:gyrodyne":1,"minecraft:bone_meal":20,"iceandfire:armor_amythest_leggings":2,"minecraft:cobweb":7,"minecraft:crimson_fence":1,"minecraft:flint_and_steel":32,"minecraft:spruce_planks":51,"minecraft:cooked_chicken":3,"minecraft:dirt":38,"alexsmobs:moose_ribs":3,"alexsmobs:cooked_kangaroo_meat":27,"minecraft:spruce_fence":98,"minecraft:iron_hoe":13,"minecraft:stone_brick_slab":33,"minecraft:wooden_axe":21,"alexsmobs:maggot":2,"brewery:bar_counter":4,"minecraft:iron_boots":1,"minecraft:cooked_beef":23,"minecraft:powder_snow_bucket":1,"minecraft:iron_leggings":1,"minecraft:cooked_mutton":11,"iceandfire:pixie_house_spruce":2,"minecraft:polished_andesite":1,"minecraft:red_nether_bricks":1,"brewery:dried_wheat":2,"minecraft:magenta_bed":5,"minecraft:red_mushroom":1,"iceandfire:dread_stone_bricks_mossy":1,"minecraft:painting":32,"irons_spellbooks:alchemist_cauldron":3,"minecraft:apple":2,"man_of_many_planes:scarlet_biplane":6,"minecraft:cracked_polished_blackstone_bricks":21,"iceandfire:ash":1,"minecraft:stone_axe":438,"brewery:beer_mug":3,"minecraft:bucket":509,"alexsmobs:animal_dictionary":1,"minecraft:splash_potion":1,"iceandfire:lectern":1,"alexsmobs:emu_egg":2},"minecraft:custom":{"minecraft:interact_with_crafting_table":200,"minecraft:open_barrel":323,"minecraft:leave_game":45,"minecraft:time_since_death":111153,"minecraft:damage_blocked_by_shield":2861,"minecraft:play_time":2218721,"minecraft:deaths":62,"minecraft:jump":29134,"minecraft:interact_with_furnace":189,"minecraft:traded_with_villager":146,"minecraft:sleep_in_bed":67,"minecraft:damage_dealt":136033,"waystones:waystone_activated":13,"minecraft:interact_with_smoker":4,"minecraft:interact_with_smithing_table":9,"minecraft:interact_with_anvil":29,"minecraft:sneak_time":85398,"minecraft:interact_with_blast_furnace":4,"minecraft:total_world_time":2218721,"minecraft:time_since_rest":33671,"minecraft:swim_one_cm":676946,"minecraft:fly_one_cm":7614156,"minecraft:open_chest":930,"minecraft:fall_one_cm":941015,"minecraft:damage_resisted":1240,"minecraft:sprint_one_cm":7827102,"minecraft:drop":1153,"minecraft:talked_to_villager":56,"minecraft:interact_with_brewingstand":2,"minecraft:walk_on_water_one_cm":537960,"minecraft:player_kills":7,"minecraft:crouch_one_cm":399428,"minecraft:mob_kills":649,"minecraft:damage_dealt_resisted":1191,"minecraft:climb_one_cm":56396,"minecraft:walk_one_cm":8761521,"minecraft:raid_win":1,"minecraft:walk_under_water_one_cm":503098,"minecraft:boat_one_cm":1856612,"minecraft:raid_trigger":2,"minecraft:damage_taken":60210,"minecraft:damage_absorbed":1570},"minecraft:crafted":{"immersive_aircraft:engine":1,"minecraft:smooth_stone":3,"minecraft:oak_sign":3,"travelersbackpack:crafting_upgrade":2,"iceandfire:armor_amythest_chestplate":1,"minecraft:blaze_powder":6,"minecraft:nether_brick":3,"brewery:beer_mug":16,"minecraft:cooked_mutton":11,"minecraft:quartz_block":5,"iceandfire:dragonbone_arrow":30,"alexsmobs:cooked_catfish":133,"iceandfire:copper_pickaxe":1,"minecraft:wooden_shovel":1,"minecraft:emerald":148,"minecraft:cooked_porkchop":9,"minecraft:jungle_boat":1,"travelersbackpack:standard":1,"minecraft:smithing_table":1,"iceandfire:wither_shard":6,"minecraft:copper_ingot":42,"immersive_aircraft:propeller":4,"iceandfire:dragonbone_sword_ice":1,"minecraft:iron_pickaxe":5,"minecraft:iron_block":3,"minecraft:gold_ingot":54,"iceandfire:dragon_horn":1,"brewery:wooden_brewingstation":1,"brewery:bar_counter":1,"minecraft:iron_nugget":18,"immersive_aircraft:biplane":1,"iceandfire:armor_amythest_helmet":2,"minecraft:bone_meal":42,"brewery:barley":2,"irons_spellbooks:graybeard_staff":1,"minecraft:spruce_fence":96,"minecraft:white_carpet":12,"travelersbackpack:blank_upgrade":12,"travelersbackpack:gold_tier_upgrade":3,"travelersbackpack:white_sleeping_bag":1,"minecraft:spruce_slab":216,"travelersbackpack:gold":1,"minecraft:stone_pickaxe":2,"man_of_many_planes:scarlet_biplane":1,"minecraft:spruce_boat":2,"alexsmobs:blood_sprayer":1,"irons_spellbooks:gold_spell_book":1,"minecraft:wheat":686,"brewery:cabinet":3,"brewery:silo_wood":2,"iceandfire:dragonbone_sword":4,"minecraft:enchanted_book":5,"simplyswords:iron_greathammer":2,"brewery:corn_seeds":3,"minecraft:iron_leggings":1,"minecraft:white_bed":4,"minecraft:oak_planks":668,"travelersbackpack:iron":1,"minecraft:barrel":4,"iceandfire:armor_amythest_leggings":1,"minecraft:stone":3,"minecraft:stone_brick_slab":24,"minecraft:bow":1,"iceandfire:dragonbone_sword_lightning":3,"immersive_aircraft:hull":10,"minecraft:chest":59,"dragonfinder:ice_dragon_eye":4,"brewery:barrel_main":1,"minecraft:ender_eye":8,"minecraft:oak_slab":12,"travelersbackpack:iron_tier_upgrade":4,"minecraft:crafting_table":16,"minecraft:spruce_planks":2354,"minecraft:wooden_pickaxe":1,"minecraft:birch_planks":52,"iceandfire:dragonbone_bow":1,"minecraft:shield":2,"minecraft:stick":4374,"minecraft:iron_ingot":42,"minecraft:stone_sword":2,"artifacts:eternal_steak":1,"minecraft:leather_boots":1,"iceandfire:dragon_stick":1,"immersive_aircraft:sail":4,"minecraft:furnace":14,"minecraft:blast_furnace":1,"minecraft:piston":2,"minecraft:iron_axe":1,"travelersbackpack:furnace_upgrade":1,"minecraft:cooked_beef":14,"minecraft:cooked_cod":1,"minecraft:crimson_planks":4,"immersive_aircraft:boiler":1,"iceandfire:tide_trident":1,"alexsmobs:cooked_kangaroo_meat":14,"minecraft:iron_sword":1,"iceandfire:armor_amythest_boots":2,"minecraft:bucket":1,"minecraft:stone_axe":3,"minecraft:bread":278,"minecraft:air":208,"minecraft:jungle_planks":2,"minecraft:white_wool":9,"immersive_aircraft:gyrodyne":2,"brewery:hops_seeds":9,"minecraft:anvil":1,"minecraft:acacia_planks":100,"minecraft:torch":60},"minecraft:mined":{"minecraft:polished_granite_slab":1,"minecraft:white_bed":11,"iceandfire:copper_pile":46,"minecraft:red_nether_bricks":4,"minecraft:crimson_trapdoor":1,"minecraft:granite":4,"minecraft:acacia_log":39,"minecraft:chiseled_polished_blackstone":1,"minecraft:stone_brick_wall":1,"minecraft:yellow_carpet":1,"minecraft:jungle_log":2,"minecraft:deepslate_bricks":2,"minecraft:oak_wall_sign":1,"minecraft:spawner":3,"minecraft:weeping_vines_plant":3,"minecraft:tall_seagrass":1,"minecraft:polished_blackstone_bricks":94,"minecraft:magma_block":3,"minecraft:cobbled_deepslate":2,"minecraft:barrel":5,"minecraft:fire":160,"minecraft:moss_carpet":2,"minecraft:deepslate_lapis_ore":4,"minecraft:fletching_table":5,"minecraft:nether_brick_stairs":3,"minecraft:water_cauldron":2,"minecraft:dirt_path":1,"iceandfire:dread_stone_bricks_cracked":10,"minecraft:player_head":1,"create:limestone":1,"minecraft:orange_bed":3,"minecraft:tripwire":2,"block_factorys_bosses:big_chain":1,"minecraft:crimson_nylium":52,"minecraft:kelp_plant":12,"minecraft:soul_fire":1,"minecraft:amethyst_cluster":1,"minecraft:powder_snow":131,"minecraft:torch":27,"minecraft:melon":36,"minecraft:dead_bush":2,"minecraft:white_stained_glass_pane":1,"minecraft:nether_brick_slab":2,"minecraft:cyan_bed":10,"minecraft:crimson_stairs":26,"minecraft:amethyst_block":15,"iceandfire:crackled_stone":1,"minecraft:wheat":53,"minecraft:magenta_bed":4,"minecraft:stone_brick_stairs":66,"minecraft:grass":219,"create:hand_crank":1,"minecraft:smooth_basalt":2,"minecraft:deepslate":2,"create:zinc_ore":2,"minecraft:deepslate_tiles":2,"iceandfire:silver_ore":1,"minecraft:dark_oak_log":1,"minecraft:nether_bricks":9,"minecraft:spruce_fence":2,"minecraft:crimson_roots":16,"minecraft:kelp":2,"minecraft:red_mushroom":1,"minecraft:white_concrete_powder":3,"minecraft:redstone_ore":4,"minecraft:packed_mud":1,"minecraft:acacia_wood":3,"minecraft:andesite":3,"block_factorys_bosses:underworld_tall_candles":10,"minecraft:cobblestone_slab":9,"minecraft:vine":42,"minecraft:bamboo_sapling":1,"irons_spellbooks:inscription_table":2,"minecraft:white_wool":26,"minecraft:smithing_table":5,"minecraft:light_gray_carpet":1,"minecraft:chiseled_nether_bricks":3,"minecraft:potted_lily_of_the_valley":1,"minecraft:brown_carpet":1,"minecraft:stone_brick_slab":30,"minecraft:dandelion":1,"minecraft:cornflower":2,"minecraft:emerald_ore":9,"minecraft:crimson_slab":1,"minecraft:campfire":2,"minecraft:copper_ore":1,"minecraft:tall_grass":20,"travelersbackpack:squid":2,"minecraft:white_carpet":23,"minecraft:spruce_log":474,"iceandfire:silver_pile":1,"minecraft:sunflower":1,"minecraft:gravel":37,"minecraft:cobweb":73,"minecraft:acacia_planks":2,"minecraft:stone_bricks":44,"block_factorys_bosses:tall_vase":1,"minecraft:fern":24,"create:deepslate_zinc_ore":1,"minecraft:spruce_planks":9,"minecraft:stone_pressure_plate":1,"minecraft:cobblestone_stairs":3,"minecraft:brewing_stand":2,"minecraft:grass_block":27,"brewery:bar_counter":3,"minecraft:cracked_polished_blackstone_bricks":39,"iceandfire:dread_spawner":2,"minecraft:mud_bricks":1,"minecraft:composter":1,"minecraft:iron_ore":37,"minecraft:anvil":1,"minecraft:azure_bluet":1,"minecraft:dark_oak_stairs":1,"iceandfire:pixie_house_spruce":2,"minecraft:azalea_leaves":2,"minecraft:polished_granite_stairs":1,"minecraft:spruce_slab":3,"iceandfire:chared_cobblestone":1,"minecraft:deepslate_redstone_ore":9,"minecraft:blackstone":112,"irons_spellbooks:alchemist_cauldron":3,"iceandfire:dragon_ice_spikes":10,"minecraft:calcite":2,"minecraft:chest":5,"iceandfire:frozen_dirt":2,"minecraft:nether_quartz_ore":23,"minecraft:cobblestone":90,"minecraft:prismarine":2,"minecraft:wall_torch":25,"minecraft:oak_planks":2,"minecraft:nether_wart_block":6,"minecraft:tnt":1,"minecraft:oak_log":281,"block_factorys_bosses:vase":1,"brewery:beer_mug":5,"minecraft:dirt":19,"minecraft:sand":3,"create:encased_chain_drive":4,"iceandfire:dread_stone_bricks":3,"minecraft:netherrack":305,"brewery:cabinet":1,"minecraft:oak_leaves":12,"minecraft:nether_gold_ore":6,"minecraft:tuff":10,"minecraft:red_carpet":9,"minecraft:dark_oak_leaves":1,"minecraft:deepslate_diamond_ore":3,"minecraft:candle":22,"gravestone:gravestone":55,"iceandfire:frozen_stone":1,"minecraft:weeping_vines":6,"travelersbackpack:white_sleeping_bag":1,"minecraft:spruce_leaves":18,"minecraft:acacia_slab":1,"minecraft:sandstone":2,"minecraft:cracked_nether_bricks":1,"minecraft:crimson_stem":1,"minecraft:large_fern":29,"minecraft:hay_block":83,"minecraft:furnace":5,"block_factorys_bosses:under_world_tall_candle_cross":1,"minecraft:stripped_spruce_log":1,"treechop:chopped_log":10,"minecraft:gold_block":16,"minecraft:nether_brick_fence":2,"minecraft:deepslate_iron_ore":1,"minecraft:bookshelf":38,"minecraft:stripped_acacia_log":1,"irons_spellbooks:firefly_jar":1,"minecraft:stone":379,"iceandfire:pixie_jar_empty":1,"minecraft:scaffolding":4,"minecraft:acacia_leaves":2,"minecraft:basalt":28,"block_factorys_bosses:underwold_candles":2,"minecraft:crafting_table":19,"minecraft:blackstone_slab":6,"minecraft:oak_wood":1,"block_factorys_bosses:rusty_prison_door":1,"brewery:corn_crop":5,"minecraft:lapis_ore":1,"minecraft:polished_blackstone_brick_stairs":3,"minecraft:cactus":1,"minecraft:beehive":1,"minecraft:sweet_berry_bush":72,"minecraft:ice":4,"minecraft:gray_bed":2,"iceandfire:ash":1,"minecraft:coal_ore":310,"minecraft:flower_pot":1,"minecraft:cracked_stone_bricks":21,"minecraft:polished_andesite":18,"create:andesite_encased_shaft":2,"minecraft:mossy_stone_bricks":4,"minecraft:crimson_fence":8,"brewery:dried_wheat":2},"minecraft:broken":{"minecraft:iron_boots":1,"minecraft:golden_sword":1,"simplyswords:iron_greathammer":2,"minecraft:shield":2,"minecraft:iron_axe":3,"minecraft:iron_pickaxe":6,"minecraft:iron_helmet":1,"minecraft:stone_pickaxe":1,"minecraft:stone_axe":3,"minecraft:wooden_axe":1,"iceandfire:armor_amythest_helmet":1},"minecraft:picked_up":{"minecraft:wooden_axe":1,"iceandfire:dread_stone_bricks":2,"minecraft:anvil":2,"minecraft:iron_chestplate":3,"waystones:warp_stone":1,"minecraft:chainmail_boots":3,"minecraft:flower_pot":2,"iceandfire:copper_sword":3,"minecraft:prismarine_shard":10,"minecraft:smithing_table":5,"minecraft:lead":2,"minecraft:enchanted_book":2,"minecraft:brewing_stand":2,"minecraft:golden_sword":1,"minecraft:amethyst_block":17,"iceandfire:manuscript":5,"minecraft:string":117,"block_factorys_bosses:wall_torch":1,"create:limestone":2,"minecraft:cooked_salmon":1,"minecraft:red_nether_bricks":1,"simplyswords:diamond_scythe":1,"minecraft:pufferfish":1,"alexsmobs:emu_feather":10,"minecraft:gold_nugget":30,"minecraft:cobbled_deepslate":22,"minecraft:crimson_fence":8,"minecraft:spruce_planks":89,"hangglider:hang_glider":6,"minecraft:melon_slice":173,"relics:blazing_flask":1,"brewery:bar_counter":3,"minecraft:beehive":3,"minecraft:weathered_cut_copper_slab":1,"minecraft:acacia_log":73,"iceandfire:lightning_dragon_flesh":35,"minecraft:cauldron":2,"minecraft:chiseled_nether_bricks":3,"travelersbackpack:iron":4,"minecraft:orange_bed":3,"minecraft:stone_sword":2,"iceandfire:armor_amythest_leggings":2,"minecraft:iron_block":1,"minecraft:carved_pumpkin":1,"minecraft:blaze_rod":6,"minecraft:snowball":101,"minecraft:birch_log":13,"iceandfire:dragonscales_black":4,"minecraft:oxidized_copper":2,"minecraft:feather":13,"minecraft:cooked_beef":9,"minecraft:water_bucket":2,"minecraft:jungle_log":3,"minecraft:dark_oak_boat":1,"minecraft:jungle_wood":1,"minecraft:flint":8,"alexsmobs:bison_fur":2,"brewery:corn_seeds":13,"relics:jellyfish_necklace":2,"alexsmobs:cooked_kangaroo_meat":14,"minecraft:magenta_bed":7,"irons_spellbooks:concentration_amulet":1,"minecraft:lantern":1,"iceandfire:armor_amythest_helmet":2,"create:encased_chain_drive":3,"artifacts:shock_pendant":2,"iceandfire:ice_dragon_blood":2,"minecraft:honeycomb":1,"iceandfire:dragonscales_amythest":98,"minecraft:chiseled_polished_blackstone":1,"irons_spellbooks:frostward_ring":5,"iceandfire:dragonscales_sapphire":22,"iceandfire:shiny_scales":8,"iceandfire:stymphalian_bird_feather":12,"minecraft:ink_sac":4,"iceandfire:lightning_dragon_heart":14,"minecraft:acacia_stairs":6,"minecraft:dark_oak_log":1,"minecraft:barrel":3,"iceandfire:chared_cobblestone":2,"minecraft:iron_hoe":2,"minecraft:stripped_acacia_log":1,"minecraft:polished_andesite":25,"alexsmobs:kangaroo_hide":29,"brewery:cabinet":1,"iceandfire:crackled_stone":1,"iceandfire:lectern":1,"minecraft:granite":2,"iceandfire:dragonbone_bow":1,"minecraft:bread":87,"minecraft:chainmail_helmet":8,"alexsmobs:maggot":4,"iceandfire:troll_leather_forest":3,"iceandfire:gorgon_head":2,"minecraft:light_gray_carpet":1,"iceandfire:raw_silver":3,"minecraft:crimson_roots":19,"minecraft:diamond_pickaxe":4,"iceandfire:dragon_skull_lightning":26,"minecraft:crafting_table":22,"iceandfire:witherbone":10,"iceandfire:dragonbone_arrow":41,"gravestone:obituary":40,"alexsmobs:cooked_catfish":20,"minecraft:acacia_door":2,"neapolitan:banana_frond":2,"minecraft:white_carpet":24,"minecraft:cracked_stone_bricks":21,"minecraft:beef":13,"minecraft:chest":5,"iceandfire:dread_shard":36,"minecraft:poppy":4,"minecraft:spruce_slab":19,"iceandfire:dragonscales_electric":16,"minecraft:egg":1,"artifacts:charm_of_sinking":4,"minecraft:spruce_fence":3,"minecraft:carrot":1,"minecraft:redstone":55,"minecraft:prismarine_crystals":3,"irons_spellbooks:alchemist_cauldron":3,"iceandfire:dragon_skull_ice":17,"irons_spellbooks:evocation_rune":1,"minecraft:tnt":1,"artifacts:everlasting_beef":1,"irons_spellbooks:gold_spell_book":5,"man_of_many_planes:scarlet_biplane":8,"minecraft:cooked_cod":2,"iceandfire:armor_amythest_chestplate":2,"minecraft:deepslate_bricks":2,"minecraft:hay_block":83,"brewery:corn":3,"minecraft:mutton":12,"alexsmobs:kangaroo_meat":20,"minecraft:white_wool":36,"minecraft:crimson_slab":1,"iceandfire:sea_serpent_fang":18,"minecraft:blackstone_slab":7,"minecraft:red_mushroom":3,"minecraft:acacia_wood":29,"irons_spellbooks:silver_ring":14,"minecraft:packed_mud":1,"minecraft:oak_log":295,"minecraft:lily_pad":2,"iceandfire:armor_copper_metal_helmet":1,"iceandfire:dragonscales_blue":6,"alexsmobs:mosquito_proboscis":3,"minecraft:paper":3,"minecraft:white_banner":2,"minecraft:kelp":12,"minecraft:stone_bricks":43,"iceandfire:pixie_jar_empty":2,"minecraft:stone_pickaxe":2,"minecraft:cobweb":7,"minecraft:glass_bottle":3,"minecraft:gray_bed":4,"minecraft:iron_sword":1,"iceandfire:copper_nugget":501,"minecraft:sweet_berries":92,"iceandfire:sea_serpent_scales_green":2,"brewery:dried_wheat":31,"minecraft:weathered_copper":2,"minecraft:gravel":34,"minecraft:crimson_stairs":26,"iceandfire:cyclops_skull":3,"minecraft:spruce_sapling":64,"minecraft:spruce_log":657,"iceandfire:dragonscales_copper":29,"irons_spellbooks:poisonward_ring":9,"travelersbackpack:standard":6,"minecraft:oak_wood":1,"iceandfire:dragon_flute":1,"minecraft:slime_ball":6,"iceandfire:pixie_house_spruce":2,"minecraft:stone_axe":2,"minecraft:painting":31,"minecraft:gray_wool":1,"iceandfire:ice_dragon_flesh":11,"minecraft:ender_pearl":3,"irons_spellbooks:scroll":2,"minecraft:wheat":107,"minecraft:nether_brick_fence":2,"brewery:dried_corn":2,"minecraft:potion":3,"minecraft:stone_brick_stairs":66,"minecraft:crimson_planks":8,"alexsmobs:gazelle_horn":9,"minecraft:raw_copper":13,"minecraft:iron_leggings":3,"travelersbackpack:quartz":2,"minecraft:oak_sign":1,"brewery:hops":29,"alexsmobs:blood_sac":10,"irons_spellbooks:arcane_essence":21,"minecraft:deepslate_tiles":2,"minecraft:red_sand":3,"alexsmobs:cooked_moose_ribs":3,"minecraft:cobblestone_slab":4,"minecraft:azalea":2,"minecraft:iron_pickaxe":7,"irons_spellbooks:inscription_table":2,"minecraft:iron_boots":3,"minecraft:furnace":7,"minecraft:tipped_arrow":1,"minecraft:stick":168,"minecraft:acacia_fence":14,"minecraft:oak_fence":1,"minecraft:torch":91,"block_factorys_bosses:vase":1,"block_factorys_bosses:underwold_candles":2,"iceandfire:dread_sword":4,"minecraft:spruce_stairs":1,"minecraft:porkchop":17,"minecraft:target":1,"iceandfire:crackled_gravel":7,"iceandfire:rotten_egg":1,"iceandfire:lightning_dragon_blood":3,"travelersbackpack:crafting_upgrade":1,"minecraft:cactus":9,"minecraft:rotten_flesh":41,"alexsmobs:emu_egg":3,"relics:aqua_walker":1,"minecraft:mangrove_roots":1,"minecraft:cod":3,"minecraft:blaze_powder":2,"irons_spellbooks:copper_spell_book":1,"minecraft:cobblestone":499,"relics:roller_skates":12,"brewery:beer_mug":11,"minecraft:magma_cream":1,"minecraft:andesite":3,"minecraft:orange_carpet":3,"minecraft:tuff":5,"create:raw_zinc":3,"minecraft:lapis_lazuli":34,"minecraft:dirt":95,"iceandfire:dragonbone_sword_ice":1,"minecraft:leather_boots":1,"irons_spellbooks:hogskin":7,"minecraft:bone":137,"minecraft:acacia_planks":8,"minecraft:bow":4,"minecraft:wheat_seeds":333,"iceandfire:armor_amythest_boots":1,"minecraft:raw_gold":14,"minecraft:mossy_stone_bricks":2,"minecraft:fletching_table":6,"minecraft:bamboo":48,"travelersbackpack:gold":12,"minecraft:prismarine":2,"minecraft:oak_planks":2,"irons_spellbooks:firefly_jar":1,"iceandfire:amphithere_feather":4,"minecraft:ghast_tear":1,"irons_spellbooks:frozen_bone":13,"minecraft:cooked_porkchop":26,"travelersbackpack:squid":3,"minecraft:sand":5,"minecraft:nether_brick_stairs":5,"minecraft:cyan_bed":13,"minecraft:oxidized_cut_copper_slab":7,"simplyswords:iron_greathammer":5,"iceandfire:dragonbone_sword_lightning":3,"irons_spellbooks:blaze_spell_book":1,"travelersbackpack:white_sleeping_bag":1,"minecraft:yellow_carpet":1,"minecraft:sugar":1,"artifacts:golden_hook":1,"minecraft:diamond":3,"minecraft:spruce_boat":19,"iceandfire:dread_stone_bricks_mossy":1,"waystones:waystone":4,"minecraft:polished_blackstone_button":1,"iceandfire:dragon_ice":4,"minecraft:cracked_polished_blackstone_bricks":22,"minecraft:crossbow":5,"minecraft:golden_apple":3,"alexsmobs:moose_ribs":3,"minecraft:emerald":44,"minecraft:oak_sapling":6,"iceandfire:tide_trident":1,"irons_spellbooks:uncommon_ink":1,"minecraft:netherrack":302,"iceandfire:silver_nugget":338,"minecraft:oak_leaves":131,"minecraft:charcoal":4,"minecraft:fishing_rod":1,"minecraft:cocoa_beans":5,"minecraft:azure_bluet":17,"minecraft:chicken":1,"iceandfire:fire_lily":1,"minecraft:brown_mushroom":2,"minecraft:wooden_pickaxe":2,"minecraft:stone_brick_wall":1,"minecraft:gold_block":9,"minecraft:chain":8,"minecraft:moss_carpet":2,"minecraft:iron_axe":1,"minecraft:wooden_sword":1,"artifacts:feral_claws":1,"minecraft:item_frame":1,"artifacts:fire_gauntlet":1,"minecraft:blackstone":91,"minecraft:candle":45,"minecraft:oak_boat":1,"minecraft:player_head":1,"irons_spellbooks:lightning_bottle":1,"minecraft:sugar_cane":21,"relics:drowned_belt":1,"minecraft:phantom_membrane":6,"iceandfire:ice_dragon_heart":5,"knightlib:small_essence":153,"minecraft:raw_iron":38,"iceandfire:dragonbone":221,"block_factorys_bosses:large_sword":2,"minecraft:copper_ingot":3,"minecraft:bowl":2,"minecraft:polished_blackstone_bricks":133,"minecraft:stone_button":16,"minecraft:stone_pressure_plate":1,"minecraft:weeping_vines":1,"minecraft:arrow":82,"block_factorys_bosses:underworld_tall_candles":10,"minecraft:saddle":2,"minecraft:skeleton_skull":3,"artifacts:eternal_steak":18,"relics:ice_skates":1,"minecraft:jungle_boat":1,"minecraft:basalt":33,"minecraft:crimson_stem":1,"minecraft:glow_ink_sac":4,"minecraft:salmon":1,"minecraft:leather":28,"minecraft:chainmail_chestplate":3,"iceandfire:dread_stone_bricks_cracked":5,"minecraft:nether_wart_block":11,"minecraft:gunpowder":9,"minecraft:cobblestone_stairs":3,"immersive_aircraft:gyrodyne":2,"brewery:beer_wheat":1,"brewery:dried_barley":2,"minecraft:cooked_mutton":1,"irons_spellbooks:common_ink":1,"minecraft:red_carpet":10,"alexsmobs:moose_antler":1,"minecraft:iron_ingot":98,"minecraft:cooked_chicken":8,"iceandfire:sea_serpent_scales_deepblue":7,"minecraft:oxidized_cut_copper":1,"minecraft:acacia_sapling":4,"knightlib:great_essence":72,"minecraft:book":112,"artifacts:obsidian_skull":1,"minecraft:stone_brick_slab":30,"iceandfire:ash":7,"minecraft:quartz":29,"minecraft:dandelion":2,"minecraft:amethyst_shard":12,"minecraft:white_bed":11,"minecraft:nether_brick_slab":3,"minecraft:spider_eye":8,"minecraft:spruce_door":2,"alexsmobs:raw_catfish":146,"minecraft:chainmail_leggings":3,"minecraft:iron_helmet":1,"minecraft:acacia_slab":1,"minecraft:black_wool":1,"minecraft:coal":426},"minecraft:killed_by":{"minecraft:stray":1,"alexsmobs:moose":1,"alexsmobs:crocodile":3,"minecraft:player":18},"minecraft:dropped":{"minecraft:iron_sword":3,"iceandfire:raw_silver":2,"minecraft:acacia_wood":26,"knightlib:small_essence":124,"minecraft:porkchop":1,"minecraft:lapis_lazuli":21,"minecraft:glow_ink_sac":4,"minecraft:glass_bottle":10,"minecraft:diamond":1,"minecraft:crafting_table":4,"minecraft:cooked_porkchop":1,"artifacts:shock_pendant":1,"minecraft:crossbow":5,"minecraft:oxidized_cut_copper_slab":7,"iceandfire:dragonscales_copper":19,"travelersbackpack:iron_tier_upgrade":1,"minecraft:fletching_table":1,"simplyswords:iron_halberd":1,"minecraft:saddle":1,"minecraft:red_carpet":1,"minecraft:red_mushroom":2,"minecraft:item_frame":1,"minecraft:emerald":36,"minecraft:packed_mud":1,"minecraft:dirt":57,"irons_spellbooks:silver_ring":1,"minecraft:stone_button":16,"iceandfire:dread_sword":3,"relics:aqua_walker":1,"iceandfire:armor_copper_metal_boots":1,"artifacts:charm_of_sinking":4,"minecraft:chain":11,"irons_spellbooks:arcane_essence":17,"alexsmobs:emu_feather":10,"minecraft:wooden_sword":1,"minecraft:gold_nugget":26,"iceandfire:copper_pickaxe":1,"minecraft:phantom_membrane":7,"minecraft:sand":2,"minecraft:sugar":1,"minecraft:iron_pickaxe":6,"iceandfire:armor_silver_metal_helmet":1,"minecraft:fishing_rod":1,"minecraft:white_wool":4,"minecraft:bone":100,"minecraft:stone_axe":1,"minecraft:goat_horn":1,"minecraft:sugar_cane":2,"alexsmobs:gazelle_horn":9,"minecraft:cooked_chicken":5,"minecraft:cobbled_deepslate":5,"alexsmobs:animal_dictionary":2,"relics:drowned_belt":1,"minecraft:wheat":17,"minecraft:rotten_flesh":56,"minecraft:oak_planks":4,"minecraft:glowstone_dust":39,"minecraft:nether_brick_fence":2,"minecraft:azure_bluet":3,"irons_spellbooks:inscription_table":1,"iceandfire:crackled_gravel":7,"iceandfire:shiny_scales":4,"travelersbackpack:gold":8,"iceandfire:sapphire_gem":2,"minecraft:tipped_arrow":1,"minecraft:deepslate_tiles":2,"minecraft:charcoal":4,"minecraft:quartz_block":5,"irons_spellbooks:cooldown_ring":1,"minecraft:leather_boots":1,"minecraft:acacia_sapling":4,"create:limestone":2,"minecraft:spruce_slab":8,"minecraft:beef":4,"iceandfire:ice_dragon_blood":2,"minecraft:acacia_fence":14,"iceandfire:manuscript":10,"alexsmobs:mosquito_proboscis":2,"minecraft:crimson_planks":8,"minecraft:enchanted_book":2,"minecraft:iron_ingot":4,"minecraft:chiseled_nether_bricks":3,"minecraft:wheat_seeds":296,"minecraft:tnt":1,"minecraft:oxidized_cut_copper":1,"minecraft:oak_fence":1,"minecraft:feather":11,"minecraft:cobblestone":90,"minecraft:prismarine_crystals":3,"minecraft:book":2,"minecraft:granite":2,"minecraft:spruce_door":1,"alexsmobs:raw_catfish":29,"brewery:corn_seeds":1,"minecraft:yellow_carpet":1,"minecraft:polished_blackstone_button":1,"minecraft:chainmail_helmet":8,"minecraft:coal":59,"minecraft:golden_apple":2,"minecraft:polished_andesite":24,"minecraft:pufferfish":1,"minecraft:cobweb":7,"minecraft:gray_wool":1,"relics:roller_skates":1,"minecraft:ink_sac":4,"iceandfire:copper_nugget":143,"knightlib:great_essence":68,"minecraft:gray_bed":1,"minecraft:wooden_axe":1,"minecraft:diamond_helmet":1,"minecraft:potion":5,"minecraft:white_banner":1,"minecraft:chainmail_leggings":3,"minecraft:paper":4,"minecraft:string":29,"minecraft:lily_pad":2,"create:raw_zinc":3,"minecraft:oxidized_copper":2,"minecraft:acacia_planks":8,"minecraft:spruce_sapling":42,"minecraft:stone_brick_slab":6,"iceandfire:silver_nugget":348,"minecraft:moss_carpet":2,"iceandfire:armor_amythest_boots":1,"minecraft:stone_sword":4,"minecraft:cocoa_beans":5,"minecraft:bowl":4,"minecraft:chicken":2,"minecraft:white_carpet":3,"iceandfire:troll_leather_forest":3,"minecraft:iron_boots":1,"iceandfire:dragonscales_electric":15,"iceandfire:dragon_skull_ice":3,"iceandfire:armor_copper_metal_helmet":1,"minecraft:spruce_fence":1,"alexsmobs:cooked_kangaroo_meat":1,"minecraft:target":1,"iceandfire:dragon_ice":4,"minecraft:cobblestone_slab":4,"minecraft:hay_block":2,"minecraft:spruce_boat":1,"minecraft:flower_pot":2,"minecraft:crimson_slab":1,"minecraft:spruce_planks":46,"minecraft:diamond_pickaxe":3,"iceandfire:silver_ingot":3,"artifacts:eternal_steak":17,"minecraft:carved_pumpkin":1,"minecraft:stone_bricks":8,"minecraft:stone_pressure_plate":1,"minecraft:spider_eye":9,"minecraft:bamboo":33,"minecraft:bow":2,"minecraft:red_sand":3,"iceandfire:dragonbone_sword_lightning":5,"waystones:waystone":2,"iceandfire:sea_serpent_fang":1,"iceandfire:dragon_skull_lightning":3,"minecraft:black_wool":1,"minecraft:candle":1,"minecraft:brown_mushroom":2,"minecraft:diamond_axe":1,"irons_spellbooks:concentration_amulet":1,"minecraft:ender_pearl":2,"iceandfire:ice_dragon_flesh":2,"minecraft:weathered_cut_copper_slab":1,"block_factorys_bosses:large_sword":2,"minecraft:lantern":1,"minecraft:leather":19,"minecraft:honeycomb":1,"minecraft:jungle_planks":3,"iceandfire:dread_stone_bricks_cracked":5,"travelersbackpack:standard":2,"alexsmobs:bison_fur":2,"minecraft:flint":3,"minecraft:cobblestone_stairs":3,"immersive_aircraft:gyrodyne":2,"minecraft:orange_carpet":3,"irons_spellbooks:hogskin":5,"iceandfire:armor_silver_metal_leggings":1,"minecraft:mutton":8,"minecraft:crimson_roots":8,"minecraft:snowball":6,"alexsmobs:cooked_catfish":18,"gravestone:obituary":98,"minecraft:amethyst_shard":8,"iceandfire:ash":7,"minecraft:polished_blackstone_bricks":37,"minecraft:acacia_door":2,"iceandfire:dread_shard":5,"minecraft:gravel":2,"iceandfire:stymphalian_bird_feather":2,"minecraft:blackstone":2,"hangglider:hang_glider":3,"minecraft:mangrove_roots":1,"brewery:dried_wheat":1,"brewery:beer_barley":1,"iceandfire:fire_lily":1,"minecraft:cooked_mutton":1,"minecraft:acacia_stairs":6,"waystones:warp_stone":2,"travelersbackpack:iron":2,"minecraft:chainmail_chestplate":3,"alexsmobs:kangaroo_hide":12,"brewery:beer_wheat":10,"minecraft:poppy":4,"minecraft:gunpowder":11,"minecraft:skeleton_skull":3,"minecraft:acacia_slab":1,"iceandfire:pixie_dust":1,"minecraft:azalea":2,"minecraft:chainmail_boots":3,"minecraft:blackstone_slab":7,"minecraft:basalt":13,"minecraft:arrow":9,"minecraft:quartz":9,"minecraft:oak_leaves":90,"minecraft:netherrack":23,"minecraft:bread":68,"iceandfire:lightning_dragon_blood":1,"iceandfire:dragonscales_sapphire":7,"minecraft:smithing_table":1,"minecraft:prismarine_shard":10,"minecraft:lead":2,"minecraft:jungle_wood":1,"minecraft:amethyst_block":3,"minecraft:copper_ingot":1,"minecraft:spruce_stairs":1,"minecraft:acacia_log":14,"minecraft:magenta_bed":1,"minecraft:stick":192,"irons_spellbooks:scroll":5,"minecraft:iron_block":1,"iceandfire:dragonscales_black":4,"minecraft:torch":27,"artifacts:obsidian_skull":1,"minecraft:nether_wart_block":9,"minecraft:melon_slice":9,"minecraft:iron_leggings":3,"minecraft:crimson_fence":7,"iceandfire:ice_dragon_heart":2,"irons_spellbooks:common_ink":1,"minecraft:cactus":1,"artifacts:feral_claws":1,"irons_spellbooks:frozen_bone":9,"minecraft:dandelion":1,"iceandfire:dragonbone":55,"minecraft:redstone":35,"minecraft:anvil":2,"irons_spellbooks:blaze_spell_book":1,"alexsmobs:maggot":2,"minecraft:kelp":12,"minecraft:sweet_berries":3,"minecraft:weathered_copper":2,"iceandfire:lightning_dragon_heart":5,"minecraft:blaze_rod":3,"minecraft:raw_copper":13,"minecraft:raw_iron":1,"iceandfire:witherbone":2,"relics:blazing_flask":2,"minecraft:flint_and_steel":1,"minecraft:deepslate_bricks":2,"irons_spellbooks:frostward_ring":2,"minecraft:filled_map":1,"iceandfire:copper_sword":4,"iceandfire:chared_cobblestone":2,"iceandfire:dragonscales_amythest":20,"minecraft:iron_chestplate":3,"travelersbackpack:quartz":1,"minecraft:andesite":3,"man_of_many_planes:scarlet_biplane":3,"travelersbackpack:crafting_upgrade":1,"minecraft:mossy_stone_bricks":1,"minecraft:oak_boat":1,"minecraft:oak_sapling":6,"minecraft:spruce_log":3,"minecraft:slime_ball":6,"minecraft:stone_pickaxe":2,"simplyswords:diamond_scythe":1,"minecraft:wooden_pickaxe":5,"minecraft:magma_cream":1,"simplyswords:iron_greathammer":1},"minecraft:killed":{"iceandfire:hippogryph":1,"iceandfire:gorgon":1,"alexsmobs:shoebill":1,"minecraft:cod":1,"irons_spellbooks:summoned_polar_bear":1,"iceandfire:stymphalian_bird":1,"minecraft:skeleton":40,"minecraft:guardian":4,"alexsmobs:leafcutter_ant":2,"minecraft:chicken":2,"alexsmobs:straddler":1,"iceandfire:dread_scuttler":1,"irons_spellbooks:archevoker":1,"minecraft:magma_cube":13,"alexsmobs:seal":5,"block_factorys_bosses:soul_skeleton":17,"iceandfire:cockatrice":1,"minecraft:pillager":9,"minecraft:zombie":43,"iceandfire:lightning_dragon":4,"block_factorys_bosses:soul_knight_wither_skeleton":9,"iceandfire:sea_serpent":3,"minecraft:cow":5,"block_factorys_bosses:dragon_guard_sword":6,"minecraft:vindicator":1,"alexsmobs:seagull":1,"iceandfire:dread_beast":8,"knightquest:bad_patch":4,"iceandfire:siren":3,"iceandfire:hippocampus":1,"minecraft:wandering_trader":2,"minecraft:ravager":2,"alexsmobs:rhinoceros":1,"minecraft:polar_bear":1,"alexsmobs:catfish":65,"alexsmobs:gelada_monkey":2,"alexsmobs:crocodile":1,"minecraft:enderman":4,"alexsmobs:hummingbird":1,"knightquest:eldknight":1,"minecraft:zombified_piglin":1,"minecraft:witch":2,"alexsmobs:anaconda":1,"minecraft:spider":22,"irons_spellbooks:summoned_skeleton":3,"minecraft:piglin_brute":12,"alexsmobs:kangaroo":24,"minecraft:piglin":50,"minecraft:pig":6,"alexsmobs:anteater":1,"minecraft:zombie_villager":2,"alexsmobs:stradpole":9,"irons_spellbooks:necromancer":5,"minecraft:creeper":18,"alexsmobs:crimson_mosquito":14,"minecraft:sheep":6,"minecraft:trader_llama":1,"alexsmobs:terrapin":2,"minecraft:ghast":5,"minecraft:stray":5,"alexsmobs:fly":1,"knightquest:gremlin":20,"minecraft:blaze":1,"irons_spellbooks:summoned_zombie":4,"minecraft:slime":11,"minecraft:phantom":6,"iceandfire:dread_thrall":14,"alexsmobs:blue_jay":1,"alexsmobs:bison":1,"minecraft:drowned":4,"iceandfire:deathworm":1,"knightquest:eldbomb":2,"minecraft:bat":1,"minecraft:hoglin":4,"alexsmobs:emu":6,"alexsmobs:gazelle":19,"alexsmobs:moose":3,"alexsmobs:crow":2,"minecraft:wither_skeleton":5,"minecraft:villager":2}},"DataVersion":3465}